InteractionPlugin/Button.py
InteractionPlugin/InteractionClient.py
InteractionPlugin/InteractionText.py
InteractionPlugin/SelectOption.py
InteractionPlugin/SlashCommand.py
InteractionPlugin/__init__.py
InteractionPlugin-0.0.7.dist-info/METADATA
InteractionPlugin-0.0.7.dist-info/WHEEL
InteractionPlugin-0.0.7.dist-info/top_level.txt
InteractionPlugin-0.0.7.dist-info/RECORD
